brandelion/__init__.py
brandelion/cli/__init__.py
brandelion/cli/analyze.py
brandelion/cli/brandelion.py
brandelion/cli/collect.py
brandelion/cli/diagnose.py
brandelion/cli/report.py
brandelion-0.1.7.dist-info/DESCRIPTION.rst
brandelion-0.1.7.dist-info/METADATA
brandelion-0.1.7.dist-info/RECORD
brandelion-0.1.7.dist-info/WHEEL
brandelion-0.1.7.dist-info/entry_points.txt
brandelion-0.1.7.dist-info/metadata.json
brandelion-0.1.7.dist-info/top_level.txt
