Metadata-Version: 2.0
Name: brandelion
Version: 0.1.7
Summary: Social media brand analytics
Home-page: https://github.com/tapilab/brandelion
Author: Aron Culotta
Author-email: aronwc@gmail.com
License: BSD
Keywords: brandelion
Platform: UNKNOWN
Classifier: Development Status :: 2 - Pre-Alpha
Classifier: Intended Audience :: Developers
Classifier: License :: OSI Approved :: BSD License
Classifier: Natural Language :: English
Classifier: Programming Language :: Python :: 2
Classifier: Programming Language :: Python :: 2.6
Classifier: Programming Language :: Python :: 2.7
Classifier: Programming Language :: Python :: 3
Classifier: Programming Language :: Python :: 3.3
Classifier: Programming Language :: Python :: 3.4
Requires-Dist: docopt
Requires-Dist: matplotlib
Requires-Dist: numpy
Requires-Dist: requests
Requires-Dist: scikit-learn
Requires-Dist: scipy
Requires-Dist: twutil
